{
  "title": "Oracle Authorization",
  "description": "",
  "difficulty": "Beginner",
  "time": "50",
  "details": {
    "steps": [
      {
        "title": "Preparation",
        "text": "step1.md"
      },
	  {
        "title": "Users and Privileges in Oracle (I)",
        "text": "step2.md"
      },
	  {
        "title": "Users and Privileges in Oracle (II)",
        "text": "step3.md"
      },
	  {
        "title": "Users and Privileges in Oracle (III)",
        "text": "step4.md"
      },
	  {
        "title": "Users and Privileges in Oracle (IV)",
        "text": "step5.md"
      },
      {
        "title": "Exercise",
        "text": "step6.md",
		"background": "step6-bg.sh"
      },
      {
        "title": "Authorization Revocation",
        "text": "step7.md"
      }
    ],
    "intro": {
      "text": "intro.md",
	  "courseData": "background.sh"
    },
    "finish": {
      "text": "finish.md"
    },
	"assets": {
        "host01": [
			{"file": "input_name", "target": "/usr/local/bin/", "chmod": "+x"}
        ]
    }
  },
  
  "environment": {
    "uilayout": "terminal",
	"uisettings": "bash",
	"exclusionPatterns": ["*verify*","*expect*"],
	"hideHiddenFiles": true
  },
  "backend": {
    "imageid": "ubuntu:2004"
  }
}